django_error_views/__init__.py
django_error_views/apps.py
django_error_views/handlers.py
django_error_views/models.py
django_error_views/urls.py
django_error_views/views.py
django_error_views/locales/pl_PL/LC_MESSAGES/django.mo
django_error_views/locales/pl_PL/LC_MESSAGES/django.po
django_error_views/templates/django_error_views/400.html
django_error_views/templates/django_error_views/403.html
django_error_views/templates/django_error_views/404.html
django_error_views/templates/django_error_views/500.html
django_error_views/templates/django_error_views/error_actions.html
django_error_views/templates/django_error_views/error_base.html
django_error_views/templates/django_error_views/sentry.html
django_error_views-0.5.1.dist-info/METADATA
django_error_views-0.5.1.dist-info/RECORD
django_error_views-0.5.1.dist-info/WHEEL
django_error_views-0.5.1.dist-info/entry_points.txt
django_error_views-0.5.1.dist-info/top_level.txt
