Metadata-Version: 2.1
Name: django-error-views
Version: 0.5.1
Summary: Verbose error views with minimal context and integration with Sentry
Home-page: https://github.com/wooyek/django-error-views
Author: Janusz Skonieczny
Author-email: js+pypi@bravelabs.pl
License: UNKNOWN
Keywords: django-error-views
Platform: UNKNOWN
Classifier: Development Status :: 2 - Pre-Alpha
Classifier: Framework :: Django :: 1.10
Classifier: Intended Audience :: Developers
Classifier: Natural Language :: English
Classifier: Programming Language :: Python :: 2
Classifier: Programming Language :: Python :: 2.7
Classifier: Programming Language :: Python :: 3
Classifier: Programming Language :: Python :: 3.4
Classifier: Programming Language :: Python :: 3.5
Classifier: Programming Language :: Python :: 3.6
Classifier: Programming Language :: Python :: 3.7
Requires-Python: >=2.7
Provides-Extra: factories
Requires-Dist: django (<2.0); python_version < "3.5"
Requires-Dist: django (>=2.0); python_version >= "3.5"
Provides-Extra: factories
Requires-Dist: factory-boy; extra == 'factories'
